olifant/__init__.py
olifant/continuous_windowing.py
olifant/mblm_model.py
olifant/nextwordpredict.py
olifant/timbl_llm.py
olifant/timbl_llm_app.py
olifant/tok.py
olifant-0.2.0.dist-info/licenses/LICENSE
olifant-0.2.0.dist-info/METADATA
olifant-0.2.0.dist-info/WHEEL
olifant-0.2.0.dist-info/entry_points.txt
olifant-0.2.0.dist-info/top_level.txt
olifant-0.2.0.dist-info/RECORD
