Metadata-Version: 2.4
Name: olifant
Version: 0.2.0
Summary: Memory-based language modeling. Eco-friendly CPU-based LLMs
Author-email: Antal van den Bosch <a.p.j.vandenbosch@uu.nl>
Maintainer-email: Antal van den Bosch <a.p.j.vandenbosch@uu.nl>
License-Expression: Apache-2.0
Project-URL: Repository, https://github.com/antalvdb/olifant.git
Classifier: Development Status :: 4 - Beta
Classifier: Intended Audience :: Developers
Requires-Python: >=3.10
License-File: LICENSE
Requires-Dist: transformers
Requires-Dist: python3-timbl
Requires-Dist: pandas
Requires-Dist: numpy
Requires-Dist: torch
Requires-Dist: codecarbon
Requires-Dist: flask
Dynamic: license-file
